cnsstat.py
cnsstat-1.0.2.dist-info/LICENSE
cnsstat-1.0.2.dist-info/METADATA
cnsstat-1.0.2.dist-info/WHEEL
cnsstat-1.0.2.dist-info/entry_points.txt
cnsstat-1.0.2.dist-info/top_level.txt
cnsstat-1.0.2.dist-info/RECORD
