Metadata-Version: 2.1
Name: cnsstat
Version: 1.0.2
Summary: Cheap-n-nasty text system status via psutil
Author-email: Nathan Fraser <ndf-zz@6-v.org>
License: MIT
Project-URL: homepage, https://github.com/ndf-zz/cnsstat
Keywords: psutil,load,cpu,memory,disk,network,thermal
Classifier: Environment :: Console
Classifier: Development Status :: 3 - Alpha
Classifier: Operating System :: OS Independent
Classifier: Programming Language :: Python :: 3
Classifier: License :: OSI Approved :: MIT License
Classifier: Topic :: System :: Monitoring
Requires-Python: >=3.9
License-File: LICENSE
Requires-Dist: psutil
